Workbook

Sheet Main
A1: Keyword | B1: Banks_Appearing | C1: Rank_Position | D1: Keyword_short | E1: Avg. monthly searches | F1: Three month change | G1: Competition | H1: Competition (indexed value) | I1: Top of page bid (low range) | J1: Top of page bid (high range) | K1: PAT / Profit (₦B)
A2: fidelity bank account Nigeria | B2: Fidelity Bank | C2: 1 | D2: Account | E2: 50000 | F2: 0 | G2: Low | H2: 4 | I2: 2.57 | J2: 18.54 | K2: {=_xlfn.XLOOKUP(TRIM(B2),TRIM('Banks '!$A$2:$A$20),'Banks '!$B$2:$B$20,,0)} -> 73.3
A3: Sterling Bank account closure | B3: Sterling Bank | C3: 5 | D3: Account Closure | E3: 500 | F3: 0 | G3: Low | H3: 2 | I3: 20.41 | J3: 266.52 | K3: {=_xlfn.XLOOKUP(TRIM(B3),TRIM('Banks '!$A$2:$A$20),'Banks '!$B$2:$B$20,,0)} -> 43.68
A4: Jaiz Bank account inquiry | B4: Jaiz Bank | C4: 4 | D4: Account Inquiry | E4: 50 | F4: 0 | G4: Low | H4: 0 | I4: 0 | J4: 0 | K4: {=_xlfn.XLOOKUP(TRIM(B4),TRIM('Banks '!$A$2:$A$20),'Banks '!$B$2:$B$20,,0)} -> 40.38
A5: Access Bank account login | B5: Access Bank | C5: 1 | D5: Account Login | E5: 50 | F5: 0 | G5: Low | H5: 0 | I5: 0 | J5: 0 | K5: {=_xlfn.XLOOKUP(TRIM(B5),TRIM('Banks '!$A$2:$A$20),'Banks '!$B$2:$B$20,,0)} -> 642.22
A6: account opening Nigeria | B6: UBA | C6: 7 | D6: Account Opening | E6: 500 | F6: 0 | G6: Low | H6: 0 | I6: 0 | J6: 0 | K6: {=_xlfn.XLOOKUP(TRIM(B6),TRIM('Banks '!$A$2:$A$20),'Banks '!$B$2:$B$20,,0)} -> 766.6
A7: account opening Nigeria | B7: UBA | C7: 9 | D7: Account Opening | E7: 500 | F7: 0 | G7: Low | H7: 0 | I7: 0 | J7: 0 | K7: {=_xlfn.XLOOKUP(TRIM(B7),TRIM('Banks '!$A$2:$A$20),'Banks '!$B$2:$B$20,,0)} -> 766.6
A8: account opening Nigeria | B8: Zenith Bank | C8: 7 | D8: Account Opening | E8: 500 | F8: 0 | G8: Low | H8: 0 | I8: 0 | J8: 0 | K8: {=_xlfn.XLOOKUP(TRIM(B8),TRIM('Banks '!$A$2:$A$20),'Banks '!$B$2:$B$20,,0)} -> 1030
A9: account opening Nigeria | B9: Zenith Bank | C9: 9 | D9: Account Opening | E9: 500 | F9: 0 | G9: Low | H9: 0 | I9: 0 | J9: 0 | K9: {=_xlfn.XLOOKUP(TRIM(B9),TRIM('Banks '!$A$2:$A$20),'Banks '!$B$2:$B$20,,0)} -> 1030
A10: FCMB account opening guide | B10: FCMB | C10: 1 | D10: Account Opening Guide | E10: 500 | F10: 0 | G10: Low | H10: 14 | I10: 31.27 | J10: 185.53 | K10: {=_xlfn.XLOOKUP(TRIM(B10),TRIM('Banks '!$A$2:$A$20),'Banks '!$B$2:$B$20,,0)} -> 23.48
A11: Lotus Bank account setup | B11: Lotus Bank | C11: 1 | D11: Account Setup | E11: 0 | F11: 0 | G11: NIL | H11: 0 | I11: 0 | J11: 0 | K11: {=_xlfn.XLOOKUP(TRIM(B11),TRIM('Banks '!$A$2:$A$20),'Banks '!$B$2:$B$20,,0)} -> 12
A12: account statement bank Nigeria | B12: UBA | C12: 2 | D12: Account Statement | E12: 50 | F12: 0 | G12: Low | H12: 0 | I12: 0 | J12: 0 | K12: {=_xlfn.XLOOKUP(TRIM(B12),TRIM('Banks '!$A$2:$A$20),'Banks '!$B$2:$B$20,,0)} -> 766.6
A13: account statement bank Nigeria | B13: UBA | C13: 4 | D13: Account Statement | E13: 50 | F13: 0 | G13: Low | H13: 0 | I13: 0 | J13: 0 | K13: {=_xlfn.XLOOKUP(TRIM(B13),TRIM('Banks '!$A$2:$A$20),'Banks '!$B$2:$B$20,,0)} -> 766.6
... A141: bank verification Nigeria | B141: UBA | C141: 4 | D141: Verification | E141: 50000 | F141: 0 | G141: Low | H141: 3 | I141: 19.53 | J141: 50.07 | K141: {=_xlfn.XLOOKUP(TRIM(B141),TRIM('Banks '!$A$2:$A$20),'Banks '!$B$2:$B$20,,0)} -> 766.6

Sheet Banks 
A1: Bank_Name | B1: PAT / Profit (₦B)
A2: Access Bank | B2: 642.22
A3: FCMB | B3: 23.48
A4: Fidelity Bank | B4: 73.3
A5: First Bank | B5: 385.2
A6: Globus Bank | B6: 3210
A7: GTBank | B7: 1017
A8: Jaiz Bank | B8: 40.38
A9: Keystone Bank | B9: 23.5
A10: Lotus Bank | B10: 12
A11: Nova Merchant Bank | B11: 3210
A12: Polaris Bank | B12: 40.4
A13: Providus Bank | B13: 50
... A20: Zenith Bank | B20: 1030
